tools/ImgTools.py
tools/PdfTools.py
tools/__init__.py
tools/entrypoints/__init__.py
tools/entrypoints/main.py
custools-0.1.0.dist-info/LICENSE
custools-0.1.0.dist-info/METADATA
custools-0.1.0.dist-info/WHEEL
custools-0.1.0.dist-info/entry_points.txt
custools-0.1.0.dist-info/top_level.txt
custools-0.1.0.dist-info/RECORD
