Metadata-Version: 2.1
Name: custools
Version: 0.1.0
Summary: A commonly used simple tools!
Home-page: https://github.com/Potato-DiGua/Tools
Author: Potato-DiGua
Author-email: 86543402@qq.com
License: MIT
Project-URL: Bug Tracker, https://github.com/Potato-DiGua/Tools/issues
Platform: UNKNOWN
Requires-Python: >=3.6
Requires-Dist: Pillow
Requires-Dist: PyPDF2
